ndx_optogenetics/spec/ndx-optogenetics.extensions.yaml
ndx_optogenetics/spec/ndx-optogenetics.namespace.yaml
ndx_optogenetics/__init__.py
ndx_optogenetics/optogenetics.py
ndx_optogenetics-0.3.0.dist-info/METADATA
ndx_optogenetics-0.3.0.dist-info/WHEEL
ndx_optogenetics-0.3.0.dist-info/licenses/LICENSE.txt
ndx_optogenetics-0.3.0.dist-info/RECORD
